runtime_generics/__init__.py
runtime_generics/py.typed
runtime_generics-3.3.1.dist-info/LICENSE
runtime_generics-3.3.1.dist-info/METADATA
runtime_generics-3.3.1.dist-info/WHEEL
runtime_generics-3.3.1.dist-info/RECORD
