Metadata-Version: 2.1
Name: runtime_generics
Version: 3.3.1
Summary: Reuse generic class type arguments at runtime.
Home-page: https://github.com/bswck/runtime_generics
License: MIT
Author: bswck
Author-email: bartoszpiotrslawecki@gmail.com
Requires-Python: >=3.8
Classifier: License :: OSI Approved :: MIT License
Classifier: Programming Language :: Python :: 3
Classifier: Programming Language :: Python :: 3.8
Classifier: Programming Language :: Python :: 3.9
Classifier: Programming Language :: Python :: 3.10
Classifier: Programming Language :: Python :: 3.11
Classifier: Programming Language :: Python :: 3.12
Requires-Dist: backframe (>=0.1.2)
Requires-Dist: typing-extensions (>=4.9.0)
Project-URL: Coverage, https://coverage-badge.samuelcolvin.workers.dev/redirect/bswck/runtime_generics
Project-URL: Documentation, https://bswck.github.io/runtime_generics
Project-URL: Distribution, https://pypi.org/project/runtime-generics/
Project-URL: Issues, https://github.com/bswck/runtime_generics/issues
